MANIFEST.in
setup.py
datatrans/__init__.py
datatrans/admin.py
datatrans/middleware.py
datatrans/models.py
datatrans/tests.py
datatrans/urls.py
datatrans/utils.py
datatrans/views.py
datatrans/locale/fr/LC_MESSAGES/django.mo
datatrans/locale/fr/LC_MESSAGES/django.po
datatrans/locale/nl/LC_MESSAGES/django.mo
datatrans/locale/nl/LC_MESSAGES/django.po
datatrans/management/__init__.py
datatrans/management/commands/__init__.py
datatrans/management/commands/deleteduplicates.py
datatrans/migrations/0001_initial.py
datatrans/migrations/0001a_remove_duplicates.py
datatrans/migrations/0002_add_unique_together.py
datatrans/migrations/0003_auto__add_field_keyvalue_content_type__add_field_keyvalue_object_id__a.py
datatrans/migrations/0003_auto__add_modelwordcount__add_fieldwordcount__add_unique_fieldwordcoun.py
datatrans/migrations/0004_add_object_links.py
datatrans/migrations/0005_auto__add_field_keyvalue_updated.py
datatrans/migrations/0006_auto__chg_field_keyvalue_field__del_unique_keyvalue_language_digest__a.py
datatrans/migrations/__init__.py
datatrans/templates/datatrans/base.html
datatrans/templates/datatrans/model_detail.html
datatrans/templates/datatrans/model_list.html
datatrans/templates/datatrans/object_list.html
datatrans/templates/datatrans/obsolete_list.html
django_datatrans.egg-info/PKG-INFO
django_datatrans.egg-info/SOURCES.txt
django_datatrans.egg-info/dependency_links.txt
django_datatrans.egg-info/not-zip-safe
django_datatrans.egg-info/top_level.txt
test_project/__init__.py
test_project/manage.py
test_project/runtests.py
test_project/settings.py
test_project/urls.py
test_project/testapp/__init__.py
test_project/testapp/admin.py
test_project/testapp/models.py
test_project/testapp/tests.py
test_project/testapp/utils.py
test_project/testapp/views.py