Metadata-Version: 1.1
Name: django-datatrans
Version: 0.1.5
Summary: Translate Django models without changing anything to existing applications and their underlying database.
Home-page: http://github.com/citylive/django-datatrans/
Author: Jef Geskens, VikingCo nv
Author-email: jef.geskens@mobilevikings.com
License: LICENSE
Platform: UNKNOWN
Classifier: Development Status :: 4 - Beta
Classifier: Intended Audience :: Developers
Classifier: License :: OSI Approved :: BSD License
Classifier: Programming Language :: Python
Classifier: Operating System :: OS Independent
Classifier: Environment :: Web Environment
Classifier: Framework :: Django
Classifier: Topic :: Software Development :: Internationalization
